MANIFEST.in
README.md
setup.cfg
setup.py
memorpy3/Address.py
memorpy3/BaseProcess.py
memorpy3/Locator.py
memorpy3/MemWorker.py
memorpy3/WinProcess.py
memorpy3/WinStructures.py
memorpy3/__init__.py
memorpy3/utils.py
memorpy3/version.py
memorpy3/wintools.py
memorpy3.egg-info/PKG-INFO
memorpy3.egg-info/SOURCES.txt
memorpy3.egg-info/dependency_links.txt
memorpy3.egg-info/not-zip-safe
memorpy3.egg-info/top_level.txt