Metadata-Version: 2.1
Name: memorpy3
Version: 2.0.0
Summary: Python 3 port of the memorypy library using ctypes to search/edit windows programs memory
Home-page: https://github.com/rbcastner/memorpy
Author: Nicolas VERDIER, Reid Castner
Author-email: contact@n1nj4.eu, rbcastner@gmail.com
Maintainer-email: rbcastner@gmail.com
License: BSD
Platform: Windows
Classifier: Programming Language :: Python :: 3
Classifier: Intended Audience :: Developers
